office_janitor/VERSION
office_janitor/__init__.py
office_janitor/app_state.py
office_janitor/c2r_uninstall.py
office_janitor/command_runner.py
office_janitor/confirm.py
office_janitor/constants.py
office_janitor/detect.py
office_janitor/elevation.py
office_janitor/exec_utils.py
office_janitor/fs_tools.py
office_janitor/guid_utils.py
office_janitor/licensing.py
office_janitor/logging_ext.py
office_janitor/main.py
office_janitor/msi_components.py
office_janitor/msi_uninstall.py
office_janitor/odt_build.py
office_janitor/off_scrub_helpers.py
office_janitor/off_scrub_native.py
office_janitor/off_scrub_scripts.py
office_janitor/plan.py
office_janitor/processes.py
office_janitor/registry_tools.py
office_janitor/repair.py
office_janitor/restore_point.py
office_janitor/safety.py
office_janitor/scrub.py
office_janitor/spinner.py
office_janitor/tasks_services.py
office_janitor/tui.py
office_janitor/ui.py
office_janitor/version.py
office_janitor-0.0.0.dist-info/licenses/license.md
office_janitor-0.0.0.dist-info/METADATA
office_janitor-0.0.0.dist-info/WHEEL
office_janitor-0.0.0.dist-info/entry_points.txt
office_janitor-0.0.0.dist-info/top_level.txt
office_janitor-0.0.0.dist-info/RECORD
