Metadata-Version: 2.4
Name: office-janitor
Version: 0.0.0
Summary: Utility for detecting, planning, and scrubbing Microsoft Office installations.
Author: Office Janitor Contributors
Classifier: Development Status :: 3 - Alpha
Classifier: Intended Audience :: System Administrators
Classifier: License :: OSI Approved :: MIT License
Classifier: Operating System :: Microsoft :: Windows
Classifier: Programming Language :: Python :: 3
Classifier: Programming Language :: Python :: 3 :: Only
Requires-Python: >=3.9
License-File: license.md
Provides-Extra: dev
Requires-Dist: black>=23.9; extra == "dev"
Requires-Dist: mypy>=1.6; extra == "dev"
Requires-Dist: pyinstaller>=6.0; extra == "dev"
Requires-Dist: pytest>=7.4; extra == "dev"
Requires-Dist: ruff>=0.1.8; extra == "dev"
Dynamic: license-file
